README.txt
setup.py
PyGS/Correlations.py
PyGS/Cosmology.py
PyGS/LuminosityFunction.py
PyGS/PowerSpectra.py
PyGS/PyGS.py
PyGS/SelectionFunction.py
PyGS/__init__.py
PyGS/utils.py
PyGS.egg-info/PKG-INFO
PyGS.egg-info/SOURCES.txt
PyGS.egg-info/dependency_links.txt
PyGS.egg-info/top_level.txt
PyGS/fort/DFT.f90
PyGS/fort/__init__.py
PyGS/fort/correlate.f90
PyGS/fort/lumfunc.f90