Metadata-Version: 1.1
Name: PyGS
Version: 0.5.0
Summary: Interactive program to deal with Galaxy Surveys.
Home-page: https://github.com/steven-murray/PyGS
Author: Steven Murray
Author-email: steven.jeanette.m@gmail.com
License: BSD
Platform: UNKNOWN
Requires: numpy
Requires: pandas
Requires: scipy
Requires: matplotlib
Requires: cosmolopy
